README.rst
setup.py
cache_tagging/__init__.py
cache_tagging.egg-info/PKG-INFO
cache_tagging.egg-info/SOURCES.txt
cache_tagging.egg-info/dependency_links.txt
cache_tagging.egg-info/top_level.txt