Metadata-Version: 1.1
Name: cache-tagging
Version: 0.7.7.40
Summary: Project has been moved to https://pypi.python.org/pypi/cache-dependencies
Home-page: https://pypi.python.org/pypi/cache-dependencies
Author: Ivan Zakrevsky
Author-email: ivzak@yandex.ru
License: BSD License
Keywords: django cache tagging
Platform: UNKNOWN
Classifier: Development Status :: 7 - Inactive
Classifier: Environment :: Web Environment
Classifier: Framework :: Django
Classifier: Intended Audience :: Developers
Classifier: License :: OSI Approved :: BSD License
Classifier: Operating System :: OS Independent
Classifier: Programming Language :: Python
Classifier: Programming Language :: Python :: 2
Classifier: Programming Language :: Python :: 2.7
Classifier: Programming Language :: Python :: 3
Classifier: Programming Language :: Python :: 3.2
Classifier: Programming Language :: Python :: 3.3
Classifier: Programming Language :: Python :: 3.4
Classifier: Topic :: Software Development :: Libraries :: Application Frameworks
Classifier: Topic :: Software Development :: Libraries :: Python Modules
